aiopenapi3/__init__.py
aiopenapi3/__main__.py
aiopenapi3/components.py
aiopenapi3/errors.py
aiopenapi3/example.py
aiopenapi3/general.py
aiopenapi3/info.py
aiopenapi3/object_base.py
aiopenapi3/openapi.py
aiopenapi3/paths.py
aiopenapi3/schemas.py
aiopenapi3/security.py
aiopenapi3/servers.py
aiopenapi3/tag.py
asyncopenapi3/__init__.py
asyncopenapi3/__main__.py
asyncopenapi3/components.py
asyncopenapi3/errors.py
asyncopenapi3/example.py
asyncopenapi3/general.py
asyncopenapi3/info.py
asyncopenapi3/object_base.py
asyncopenapi3/openapi.py
asyncopenapi3/paths.py
asyncopenapi3/schemas.py
asyncopenapi3/security.py
asyncopenapi3/servers.py
asyncopenapi3/tag.py
asyncopenapi3-1.8.2.1.dist-info/LICENSE
asyncopenapi3-1.8.2.1.dist-info/METADATA
asyncopenapi3-1.8.2.1.dist-info/WHEEL
asyncopenapi3-1.8.2.1.dist-info/top_level.txt
asyncopenapi3-1.8.2.1.dist-info/RECORD
