Metadata-Version: 2.1
Name: asyncopenapi3
Version: 1.8.2.1
Summary: Async Client and Validator of OpenAPI 3 Specifications
Home-page: https://github.com/smurfix/openapi3
Author: smurf@noris.de
License: BSD 3-Clause License
License-File: LICENSE
Requires-Dist: PyYaml
Requires-Dist: httpx
Provides-Extra: test
Requires-Dist: anyio==4.6.2; extra == "test"
Requires-Dist: fastapi==0.110.0; extra == "test"
Requires-Dist: hypercorn==0.17.3; extra == "test"
Requires-Dist: pydantic==2.9.2; extra == "test"
Requires-Dist: pylint==3.3.1; extra == "test"
Requires-Dist: pytest==8.3.3; extra == "test"
Requires-Dist: respx==0.21.1; extra == "test"
